{
  "Index" : 3,
  "Name" : "Guard",
  "Image" : "Guard",
  "AI" : 6,
  "Effect" : 0,
  "ViewRange" : 7,
  "CoolEye" : 0,
  "Level" : 0,
  "HP" : 9999,
  "Accuracy" : 255,
  "Agility" : 255,
  "Light" : 20,
  "MinAC" : 255,
  "MaxAC" : 255,
  "MinMAC" : 255,
  "MaxMAC" : 255,
  "MinDC" : 255,
  "MaxDC" : 255,
  "MinMC" : 255,
  "MaxMC" : 255,
  "MinSC" : 255,
  "MaxSC" : 255,
  "AttackSpeed" : 2000,
  "MoveSpeed" : 0,
  "Experience" : 0,
  "CanTame" : false,
  "CanPush" : false,
  "AutoRev" : false,
  "Undead" : false
}
