{
  "Index" : 78,
  "Name" : "GiantKeratoid",
  "Image" : "GiantKeratoid",
  "AI" : 0,
  "Effect" : 0,
  "ViewRange" : 7,
  "CoolEye" : 0,
  "Level" : 27,
  "HP" : 250,
  "Accuracy" : 5,
  "Agility" : 8,
  "Light" : 5,
  "MinAC" : 0,
  "MaxAC" : 0,
  "MinMAC" : 0,
  "MaxMAC" : 0,
  "MinDC" : 7,
  "MaxDC" : 15,
  "MinMC" : 0,
  "MaxMC" : 0,
  "MinSC" : 0,
  "MaxSC" : 0,
  "AttackSpeed" : 2500,
  "MoveSpeed" : 1000,
  "Experience" : 480,
  "CanTame" : true,
  "CanPush" : true,
  "AutoRev" : true,
  "Undead" : false
}
