{
  "Index" : 323,
  "Name" : "CrystalSpider",
  "Image" : "CrystalSpider",
  "AI" : 37,
  "Effect" : 0,
  "ViewRange" : 14,
  "CoolEye" : 0,
  "Level" : 54,
  "HP" : 1170,
  "Accuracy" : 15,
  "Agility" : 16,
  "Light" : 5,
  "MinAC" : 18,
  "MaxAC" : 18,
  "MinMAC" : 20,
  "MaxMAC" : 20,
  "MinDC" : 42,
  "MaxDC" : 64,
  "MinMC" : 20,
  "MaxMC" : 50,
  "MinSC" : 0,
  "MaxSC" : 0,
  "AttackSpeed" : 1700,
  "MoveSpeed" : 900,
  "Experience" : 5000,
  "CanTame" : true,
  "CanPush" : true,
  "AutoRev" : true,
  "Undead" : false
}
