{
  "Index" : 413,
  "Name" : "HellPirate",
  "Image" : "HellPirate",
  "AI" : 0,
  "Effect" : 0,
  "ViewRange" : 10,
  "CoolEye" : 0,
  "Level" : 60,
  "HP" : 980,
  "Accuracy" : 18,
  "Agility" : 17,
  "Light" : 0,
  "MinAC" : 14,
  "MaxAC" : 14,
  "MinMAC" : 17,
  "MaxMAC" : 17,
  "MinDC" : 11,
  "MaxDC" : 27,
  "MinMC" : 0,
  "MaxMC" : 0,
  "MinSC" : 0,
  "MaxSC" : 0,
  "AttackSpeed" : 1000,
  "MoveSpeed" : 1800,
  "Experience" : 11000,
  "CanTame" : false,
  "CanPush" : true,
  "AutoRev" : true,
  "Undead" : false
}
