{
  "Index" : 75,
  "FileName" : "D023A",
  "Title" : "AncientTemple_2F",
  "MiniMap" : 7,
  "BigMap" : 0,
  "Music" : 0,
  "Light" : "Night",
  "MapDarkLight" : 0,
  "MineIndex" : 0,
  "NoTeleport" : false,
  "NoReconnect" : true,
  "NoRandom" : true,
  "NoEscape" : false,
  "NoRecall" : true,
  "NoDrug" : false,
  "NoPosition" : true,
  "NoFight" : false,
  "NoThrowItem" : false,
  "NoDropPlayer" : false,
  "NoDropMonster" : false,
  "NoNames" : false,
  "NoMount" : true,
  "NeedBridle" : false,
  "Fight" : false,
  "NeedHole" : false,
  "Fire" : false,
  "Lightning" : false,
  "NoTownTeleport" : false,
  "NoReincarnation" : false,
  "NoReconnectMap" : "D022",
  "FireDamage" : 0,
  "LightningDamage" : 0,
  "SafeZones" : [],
  "Movements" : [{
      "MapIndex" : 74,
      "Source" : {
        "X" : 198,
        "Y" : 194
      },
      "Destination" : {
        "X" : 250,
        "Y" : 206
      },
      "NeedHole" : false,
      "NeedMove" : false,
      "ConquestIndex" : 0
    }, {
      "MapIndex" : 74,
      "Source" : {
        "X" : 198,
        "Y" : 193
      },
      "Destination" : {
        "X" : 250,
        "Y" : 205
      },
      "NeedHole" : false,
      "NeedMove" : false,
      "ConquestIndex" : 0
    }, {
      "MapIndex" : 76,
      "Source" : {
        "X" : 52,
        "Y" : 366
      },
      "Destination" : {
        "X" : 16,
        "Y" : 19
      },
      "NeedHole" : false,
      "NeedMove" : false,
      "ConquestIndex" : 0
    }],
  "Respawns" : [{
      "MonsterIndex" : 259,
      "Location" : {
        "X" : 200,
        "Y" : 200
      },
      "Count" : 40,
      "Spread" : 200,
      "Delay" : 3,
      "RandomDelay" : 0,
      "Direction" : 0,
      "RoutePath" : "",
      "RespawnIndex" : 1040,
      "SaveRespawnTime" : false,
      "RespawnTicks" : 0
    }, {
      "MonsterIndex" : 260,
      "Location" : {
        "X" : 200,
        "Y" : 200
      },
      "Count" : 50,
      "Spread" : 200,
      "Delay" : 3,
      "RandomDelay" : 0,
      "Direction" : 0,
      "RoutePath" : "",
      "RespawnIndex" : 1041,
      "SaveRespawnTime" : false,
      "RespawnTicks" : 0
    }, {
      "MonsterIndex" : 261,
      "Location" : {
        "X" : 200,
        "Y" : 200
      },
      "Count" : 50,
      "Spread" : 200,
      "Delay" : 3,
      "RandomDelay" : 0,
      "Direction" : 0,
      "RoutePath" : "",
      "RespawnIndex" : 1042,
      "SaveRespawnTime" : false,
      "RespawnTicks" : 0
    }, {
      "MonsterIndex" : 262,
      "Location" : {
        "X" : 200,
        "Y" : 200
      },
      "Count" : 40,
      "Spread" : 200,
      "Delay" : 3,
      "RandomDelay" : 0,
      "Direction" : 0,
      "RoutePath" : "",
      "RespawnIndex" : 1043,
      "SaveRespawnTime" : false,
      "RespawnTicks" : 0
    }, {
      "MonsterIndex" : 263,
      "Location" : {
        "X" : 200,
        "Y" : 200
      },
      "Count" : 2,
      "Spread" : 200,
      "Delay" : 60,
      "RandomDelay" : 0,
      "Direction" : 0,
      "RoutePath" : "",
      "RespawnIndex" : 1044,
      "SaveRespawnTime" : false,
      "RespawnTicks" : 0
    }, {
      "MonsterIndex" : 81,
      "Location" : {
        "X" : 200,
        "Y" : 200
      },
      "Count" : 10,
      "Spread" : 200,
      "Delay" : 3,
      "RandomDelay" : 0,
      "Direction" : 100,
      "RoutePath" : "",
      "RespawnIndex" : 1045,
      "SaveRespawnTime" : false,
      "RespawnTicks" : 0
    }, {
      "MonsterIndex" : 81,
      "Location" : {
        "X" : 200,
        "Y" : 200
      },
      "Count" : 10,
      "Spread" : 200,
      "Delay" : 3,
      "RandomDelay" : 0,
      "Direction" : 100,
      "RoutePath" : "",
      "RespawnIndex" : 1046,
      "SaveRespawnTime" : false,
      "RespawnTicks" : 0
    }, {
      "MonsterIndex" : 81,
      "Location" : {
        "X" : 200,
        "Y" : 200
      },
      "Count" : 10,
      "Spread" : 200,
      "Delay" : 3,
      "RandomDelay" : 0,
      "Direction" : 100,
      "RoutePath" : "",
      "RespawnIndex" : 1047,
      "SaveRespawnTime" : false,
      "RespawnTicks" : 0
    }, {
      "MonsterIndex" : 81,
      "Location" : {
        "X" : 200,
        "Y" : 200
      },
      "Count" : 10,
      "Spread" : 200,
      "Delay" : 3,
      "RandomDelay" : 0,
      "Direction" : 0,
      "RoutePath" : "",
      "RespawnIndex" : 1048,
      "SaveRespawnTime" : false,
      "RespawnTicks" : 0
    }],
  "NPCs" : [],
  "MineZones" : [],
  "ActiveCoords" : []
}
