{
  "Index" : 88,
  "FileName" : "D2004",
  "Title" : "BlackDragonDungeon_2F",
  "MiniMap" : 125,
  "BigMap" : 0,
  "Music" : 0,
  "Light" : "Night",
  "MapDarkLight" : 0,
  "MineIndex" : 0,
  "NoTeleport" : false,
  "NoReconnect" : false,
  "NoRandom" : false,
  "NoEscape" : false,
  "NoRecall" : false,
  "NoDrug" : false,
  "NoPosition" : false,
  "NoFight" : false,
  "NoThrowItem" : false,
  "NoDropPlayer" : false,
  "NoDropMonster" : false,
  "NoNames" : false,
  "NoMount" : true,
  "NeedBridle" : false,
  "Fight" : false,
  "NeedHole" : false,
  "Fire" : false,
  "Lightning" : false,
  "NoTownTeleport" : false,
  "NoReincarnation" : false,
  "NoReconnectMap" : "",
  "FireDamage" : 0,
  "LightningDamage" : 0,
  "SafeZones" : [],
  "Movements" : [{
      "MapIndex" : 87,
      "Source" : {
        "X" : 77,
        "Y" : 76
      },
      "Destination" : {
        "X" : 30,
        "Y" : 81
      },
      "NeedHole" : false,
      "NeedMove" : false,
      "ConquestIndex" : 0
    }, {
      "MapIndex" : 87,
      "Source" : {
        "X" : 77,
        "Y" : 77
      },
      "Destination" : {
        "X" : 30,
        "Y" : 92
      },
      "NeedHole" : false,
      "NeedMove" : false,
      "ConquestIndex" : 0
    }, {
      "MapIndex" : 89,
      "Source" : {
        "X" : 19,
        "Y" : 16
      },
      "Destination" : {
        "X" : 84,
        "Y" : 86
      },
      "NeedHole" : false,
      "NeedMove" : false,
      "ConquestIndex" : 0
    }, {
      "MapIndex" : 89,
      "Source" : {
        "X" : 20,
        "Y" : 16
      },
      "Destination" : {
        "X" : 85,
        "Y" : 85
      },
      "NeedHole" : false,
      "NeedMove" : false,
      "ConquestIndex" : 0
    }],
  "Respawns" : [{
      "MonsterIndex" : 269,
      "Location" : {
        "X" : 70,
        "Y" : 67
      },
      "Count" : 6,
      "Spread" : 50,
      "Delay" : 3,
      "RandomDelay" : 0,
      "Direction" : 0,
      "RoutePath" : "",
      "RespawnIndex" : 1128,
      "SaveRespawnTime" : false,
      "RespawnTicks" : 0
    }, {
      "MonsterIndex" : 271,
      "Location" : {
        "X" : 70,
        "Y" : 67
      },
      "Count" : 6,
      "Spread" : 50,
      "Delay" : 3,
      "RandomDelay" : 0,
      "Direction" : 0,
      "RoutePath" : "",
      "RespawnIndex" : 1129,
      "SaveRespawnTime" : false,
      "RespawnTicks" : 0
    }, {
      "MonsterIndex" : 167,
      "Location" : {
        "X" : 70,
        "Y" : 67
      },
      "Count" : 10,
      "Spread" : 100,
      "Delay" : 3,
      "RandomDelay" : 0,
      "Direction" : 0,
      "RoutePath" : "",
      "RespawnIndex" : 1130,
      "SaveRespawnTime" : false,
      "RespawnTicks" : 0
    }, {
      "MonsterIndex" : 271,
      "Location" : {
        "X" : 37,
        "Y" : 51
      },
      "Count" : 6,
      "Spread" : 50,
      "Delay" : 3,
      "RandomDelay" : 0,
      "Direction" : 0,
      "RoutePath" : "",
      "RespawnIndex" : 1131,
      "SaveRespawnTime" : false,
      "RespawnTicks" : 0
    }, {
      "MonsterIndex" : 269,
      "Location" : {
        "X" : 37,
        "Y" : 51
      },
      "Count" : 6,
      "Spread" : 50,
      "Delay" : 3,
      "RandomDelay" : 0,
      "Direction" : 0,
      "RoutePath" : "",
      "RespawnIndex" : 1132,
      "SaveRespawnTime" : false,
      "RespawnTicks" : 0
    }, {
      "MonsterIndex" : 269,
      "Location" : {
        "X" : 37,
        "Y" : 51
      },
      "Count" : 6,
      "Spread" : 50,
      "Delay" : 3,
      "RandomDelay" : 0,
      "Direction" : 0,
      "RoutePath" : "",
      "RespawnIndex" : 1133,
      "SaveRespawnTime" : false,
      "RespawnTicks" : 0
    }, {
      "MonsterIndex" : 269,
      "Location" : {
        "X" : 37,
        "Y" : 51
      },
      "Count" : 6,
      "Spread" : 50,
      "Delay" : 3,
      "RandomDelay" : 0,
      "Direction" : 0,
      "RoutePath" : "",
      "RespawnIndex" : 1134,
      "SaveRespawnTime" : false,
      "RespawnTicks" : 0
    }, {
      "MonsterIndex" : 271,
      "Location" : {
        "X" : 39,
        "Y" : 36
      },
      "Count" : 6,
      "Spread" : 50,
      "Delay" : 3,
      "RandomDelay" : 0,
      "Direction" : 0,
      "RoutePath" : "",
      "RespawnIndex" : 1135,
      "SaveRespawnTime" : false,
      "RespawnTicks" : 0
    }, {
      "MonsterIndex" : 269,
      "Location" : {
        "X" : 39,
        "Y" : 36
      },
      "Count" : 6,
      "Spread" : 50,
      "Delay" : 3,
      "RandomDelay" : 0,
      "Direction" : 0,
      "RoutePath" : "",
      "RespawnIndex" : 1136,
      "SaveRespawnTime" : false,
      "RespawnTicks" : 0
    }, {
      "MonsterIndex" : 165,
      "Location" : {
        "X" : 39,
        "Y" : 36
      },
      "Count" : 10,
      "Spread" : 100,
      "Delay" : 3,
      "RandomDelay" : 0,
      "Direction" : 0,
      "RoutePath" : "",
      "RespawnIndex" : 1137,
      "SaveRespawnTime" : false,
      "RespawnTicks" : 0
    }, {
      "MonsterIndex" : 270,
      "Location" : {
        "X" : 39,
        "Y" : 36
      },
      "Count" : 1,
      "Spread" : 50,
      "Delay" : 45,
      "RandomDelay" : 0,
      "Direction" : 0,
      "RoutePath" : "",
      "RespawnIndex" : 1138,
      "SaveRespawnTime" : false,
      "RespawnTicks" : 0
    }, {
      "MonsterIndex" : 272,
      "Location" : {
        "X" : 39,
        "Y" : 36
      },
      "Count" : 1,
      "Spread" : 50,
      "Delay" : 45,
      "RandomDelay" : 0,
      "Direction" : 0,
      "RoutePath" : "",
      "RespawnIndex" : 1139,
      "SaveRespawnTime" : false,
      "RespawnTicks" : 0
    }],
  "NPCs" : [],
  "MineZones" : [],
  "ActiveCoords" : []
}
